pyqt5_connections_mem_speed.py
pyqt_sandals.py
pyqt_test_sandals.py
pysandals-0.1.dist-info/DESCRIPTION.rst
pysandals-0.1.dist-info/METADATA
pysandals-0.1.dist-info/RECORD
pysandals-0.1.dist-info/WHEEL
pysandals-0.1.dist-info/metadata.json
pysandals-0.1.dist-info/top_level.txt
