Metadata-Version: 2.0
Name: pysandals
Version: 0.1
Summary: Various utility classes and function useful in Python apps or associated unit tests
Home-page: https://github.com/schollii/sandals
Author: Oliver Schoenborn
Author-email: oliver.schoenborn@gmail.com
License: MIT
Platform: UNKNOWN
